Workbook

Sheet Задание 1
B2: Цель
C3: Изучить существующие подходы к расчету вознаграждения авторам на видеоплатформах, сравнить их и выбрать наиболее подходящий для VK Видео
B5: Что нужно сделать
B6: 1. | C6: Собрать информацию по методам начисления вознаграждения и заполнить таблицу по форме:
C8: Метод начисления | D8: Описание | E8: Особенности | F8: Какие платформы используют
C9: ... | D9: ... | E9: ... | F9: ...
C10: ... | D10: ... | E10: ... | F10: ...
C12: Рассмотреть минимум 3 метода начисления вознаграждения авторам
C13: – Оплата за просмотры
C14: – Оплата за рекламные просмотры
C15: – Revenue Share
C16: – Оплата за вовлеченность (лайки, комментарии, репосты)
C17: – Гибридная модель
C18: – Свой вариант
B20: 2. | C20: На основе анализа заполненной таблицы выбрать один метод, который ты бы применил для партнерской программы VK Видео
B22: 3. | C22: Подготовить первый слайд презентации
C23: Слайд должен содержать:
C24: – Краткую сравнительную понятную характеристику методов
C25: – Выделение выбранного метода
C26: – Обоснование: почему ты выбираешь именно этот метод (2–4 предложения с аргументами)

Sheet Задание 1(Рабочий лист)
A3: 1. Сравнительная таблица методов начисления
A5: Метод начисления | B5: Описание | C5: Особенности | D5: Какие платформы используют
A6: Оплата за просмотры | B6: Фиксированная или динамическая ставка за каждые 1000 просмотров (RPM) | C6: Простой и прозрачный расчёт. Мотивирует количество просмотров, но слабо учитывает качество и может поощрять кликбейт. Платформа платит из своего кармана. | D6: TikTok (Creator Fund, раньше), Facebook* (бонус за просмотры) | F6: * - запрещено на территории РФ
A7: Оплата за рекламные просмотры | B7: Выплата зависит от числа показов рекламы внутри видео и CPM (стоимости 1000 показов). | C7: Прямо зависит от количества рекламы, которую досмотрели зрители. Высокая зависимость от рекламодателей. | D7: YouTube (AdSense, партнёрская программа)
A8: Revenue Share | B8: Платформа делит часть своей рекламной или подписочной выручки с автором (обычно 50–70%). | C8: Самая справедливая модель: интересы платформы и автора совпадают. Зависит от качества аудитории, тематики и эффективности рекламы. | D8: YouTube (55% автору), Twitch (50/50), VK Donut
A9: Оплата за вовлеченность | B9: Бонус за лайки, комментарии, репосты, сохранения (например, 0,01₽ за реакцию). | C9: Сильно мотивирует качество контента и лояльность аудитории. Сложнее считать и проверять | D9: Instagram (раньше бонусы за лайки)*, Telegram (звёзды)
A10: Гибридная модель | B10: Комбинация нескольких методов (например, Revenue Share + бонус за вовлечённость/досмотры) | C10: Самая гибкая. Позволяет одновременно стимулировать и количество просмотров, и качество. Минимальные риски для платформы. | D10: YouTube (частично: Super Thanks + AdSense), TikTok (новый фонд)
A11: Свой вариант: Смешанная с коэффициентом качества | B11: Revenue Share (например, 50%) + множитель за вовлеченность (нормированный по тематике). | C11: Базовая доля от рекламы + гарантированная минимальная ставка за хорошие досмотры. Защищает авторов даже при слабой монетизации рекламы. | D11: Предлагаю именно для VK Видео

Sheet Задание 2
B2: Цель
C3: На основе выбранного метода начисления в задании 1 рассчитать выплаты авторам, оценить распределение бюджета по тематикам и определить ключевые статистические показатели.
B6: Что нужно сделать
B7: 1. | C7: Собрать таблицу с данным для расчета вознаграждения (Задание 2 (Инструкция))
B8: 2. | C8: Посчитать выплату по каждому автору, используя метод, который ты выбрал в задании 1
B9: 3. | C9: Собрать табличку, состоящую из обязательных столбиков
B10: 4. | C10: Можно добавить дополнительные столбики, которые покажут правильность выбора метода
C12: Обязательные столбики
C13: Тематика | D13: Кол-во авторов | E13: Средняя выплата | F13: Медианная выплата | G13: Выплата | H13: Доля выплат топ-10% авторов
C14: ... | D14: ... | E14: ... | F14: ... | G14: ... | H14: ...
C15: ... | D15: ... | E15: ... | F15: ... | G15: ... | H15: ...
B17: 5. | C17: Подготовить второй слайд презентации
C18: – Результаты расчетов
C19: – Краткий комментарий о различиях между тематиками (если они заметны)

Sheet Задание 2.2
A1: Сводная таблица по тематикам
A2: Тематика | B2: Кол-во авторов | C2: Средняя выплата | D2: Медианная выплата | E2: Выплата | F2: Доля выплат топ-10% авторов | G2: Средние просмотры | H2: Реакций на 1000 просмотров | I2: Выручка на 1000 просмотров | J2: Выплата на 1000 просмотров
A3: Детский контент | B3: =COUNTIF('Задание 2 (Рабочий лист)'!$B$3:$B$502, A3) -> 80 | C3: =AVERAGEIF('Задание 2 (Рабочий лист)'!$B$3:$B$502, A3, 'Задание 2 (Рабочий лист)'!$I$3:$I$502) -> 39498.5 | D3: =IFERROR(__xludf.DUMMYFUNCTION("MEDIAN(FILTER('Задание 2 (Рабочий лист)'!$I$3:$I$502, 'Задание 2 (Рабочий лист)'!$B$3:$B$502 = A3)) "),4135.475) -> 4135.475 | E3: =SUMIF('Задание 2 (Рабочий лист)'!$B$3:$B$502, A3, 'Задание 2 (Рабочий лист)'!$I$3:$I$502) -> 3159880 | F3: =IFERROR(__xludf.DUMMYFUNCTION("SUM(ARRAY_CONSTRAIN(SORT(FILTER('Задание 2 (Рабочий лист)'!$I$2:$I$502, 'Задание 2 (Рабочий лист)'!$B$2:$B$502 = A3), 1, FALSE), ROUND(COUNTIF('Задание 2 (Рабочий лист)'!$B$2:$B$502, A3) * 0.1), 1)) / SUMIF('Задание 2 (Рабочий лист)'!$B$2:$B$502, A3, 'Зад"&"ание 2 (Рабочий лист)'!$I$2:$I$502) "),0.6481295544391857) -> 0.64812955 | G3: =AVERAGEIF('Задание 2 (Рабочий лист)'!$B$3:$B$502, A3, 'Задание 2 (Рабочий лист)'!$E$3:$E$502) -> 886450.01 | H3: =SUMIF('Задание 2 (Рабочий лист)'!$B$3:$B$502, A3, 'Задание 2 (Рабочий лист)'!$H$3:$H$502) / SUMIF('Задание 2 (Рабочий лист)'!$B$3:$B$502, A3, 'Задание 2 (Рабочий лист)'!$E$3:$E$502) * 1000 -> 5.4352473 | I3: =SUMIF('Задание 2 (Рабочий лист)'!$B$3:$B$502, A3, 'Задание 2 (Рабочий лист)'!$G$3:$G$502) / SUMIF('Задание 2 (Рабочий лист)'!$B$3:$B$502, A3, 'Задание 2 (Рабочий лист)'!$E$3:$E$502) * 1000 -> 89.007429 | J3: =SUMIF('Задание 2 (Рабочий лист)'!$B$3:$B$502, A3, 'Задание 2 (Рабочий лист)'!$I$3:$I$502) / SUMIF('Задание 2 (Рабочий лист)'!$B$3:$B$502, A3, 'Задание 2 (Рабочий лист)'!$E$3:$E$502) * 1000 -> 44.558068
A4: Спорт | B4: =COUNTIF('Задание 2 (Рабочий лист)'!$B$3:$B$502, A4) -> 100 | C4: =AVERAGEIF('Задание 2 (Рабочий лист)'!$B$3:$B$502, A4, 'Задание 2 (Рабочий лист)'!$I$3:$I$502) -> 58990.8 | D4: =IFERROR(__xludf.DUMMYFUNCTION("MEDIAN(FILTER('Задание 2 (Рабочий лист)'!$I$3:$I$502, 'Задание 2 (Рабочий лист)'!$B$3:$B$502 = A4)) "),9886.54) -> 9886.54 | E4: =SUMIF('Задание 2 (Рабочий лист)'!$B$3:$B$502, A4, 'Задание 2 (Рабочий лист)'!$I$3:$I$502) -> 5899080 | F4: =IFERROR(__xludf.DUMMYFUNCTION("SUM(ARRAY_CONSTRAIN(SORT(FILTER('Задание 2 (Рабочий лист)'!$I$2:$I$502, 'Задание 2 (Рабочий лист)'!$B$2:$B$502 = A4), 1, FALSE), ROUND(COUNTIF('Задание 2 (Рабочий лист)'!$B$2:$B$502, A4) * 0.1), 1)) / SUMIF('Задание 2 (Рабочий лист)'!$B$2:$B$502, A4, 'Зад"&"ание 2 (Рабочий лист)'!$I$2:$I$502) "),0.5126589511640708) -> 0.51265895 | G4: =AVERAGEIF('Задание 2 (Рабочий лист)'!$B$3:$B$502, A4, 'Задание 2 (Рабочий лист)'!$E$3:$E$502) -> 961354.66 | H4: =SUMIF('Задание 2 (Рабочий лист)'!$B$3:$B$502, A4, 'Задание 2 (Рабочий лист)'!$H$3:$H$502) / SUMIF('Задание 2 (Рабочий лист)'!$B$3:$B$502, A4, 'Задание 2 (Рабочий лист)'!$E$3:$E$502) * 1000 -> 5.3732407 | I4: =SUMIF('Задание 2 (Рабочий лист)'!$B$3:$B$502, A4, 'Задание 2 (Рабочий лист)'!$G$3:$G$502) / SUMIF('Задание 2 (Рабочий лист)'!$B$3:$B$502, A4, 'Задание 2 (Рабочий лист)'!$E$3:$E$502) * 1000 -> 122.61686 | J4: =SUMIF('Задание 2 (Рабочий лист)'!$B$3:$B$502, A4, 'Задание 2 (Рабочий лист)'!$I$3:$I$502) / SUMIF('Задание 2 (Рабочий лист)'!$B$3:$B$502, A4, 'Задание 2 (Рабочий лист)'!$E$3:$E$502) * 1000 -> 61.362161
A5: Игры | B5: =COUNTIF('Задание 2 (Рабочий лист)'!$B$3:$B$502, A5) -> 100 | C5: =AVERAGEIF('Задание 2 (Рабочий лист)'!$B$3:$B$502, A5, 'Задание 2 (Рабочий лист)'!$I$3:$I$502) -> 52187.29 | D5: =IFERROR(__xludf.DUMMYFUNCTION("MEDIAN(FILTER('Задание 2 (Рабочий лист)'!$I$3:$I$502, 'Задание 2 (Рабочий лист)'!$B$3:$B$502 = A5)) "),7782.66) -> 7782.66 | E5: =SUMIF('Задание 2 (Рабочий лист)'!$B$3:$B$502, A5, 'Задание 2 (Рабочий лист)'!$I$3:$I$502) -> 5218729 | F5: =IFERROR(__xludf.DUMMYFUNCTION("SUM(ARRAY_CONSTRAIN(SORT(FILTER('Задание 2 (Рабочий лист)'!$I$2:$I$502, 'Задание 2 (Рабочий лист)'!$B$2:$B$502 = A5), 1, FALSE), ROUND(COUNTIF('Задание 2 (Рабочий лист)'!$B$2:$B$502, A5) * 0.1), 1)) / SUMIF('Задание 2 (Рабочий лист)'!$B$2:$B$502, A5, 'Зад"&"ание 2 (Рабочий лист)'!$I$2:$I$502) "),0.44881700334002056) -> 0.448817 | G5: =AVERAGEIF('Задание 2 (Рабочий лист)'!$B$3:$B$502, A5, 'Задание 2 (Рабочий лист)'!$E$3:$E$502) -> 1103693.7 | H5: =SUMIF('Задание 2 (Рабочий лист)'!$B$3:$B$502, A5, 'Задание 2 (Рабочий лист)'!$H$3:$H$502) / SUMIF('Задание 2 (Рабочий лист)'!$B$3:$B$502, A5, 'Задание 2 (Рабочий лист)'!$E$3:$E$502) * 1000 -> 5.2860137 | I5: =SUMIF('Задание 2 (Рабочий лист)'!$B$3:$B$502, A5, 'Задание 2 (Рабочий лист)'!$G$3:$G$502) / SUMIF('Задание 2 (Рабочий лист)'!$B$3:$B$502, A5, 'Задание 2 (Рабочий лист)'!$E$3:$E$502) * 1000 -> 94.46271 | J5: =SUMIF('Задание 2 (Рабочий лист)'!$B$3:$B$502, A5, 'Задание 2 (Рабочий лист)'!$I$3:$I$502) / SUMIF('Задание 2 (Рабочий лист)'!$B$3:$B$502, A5, 'Задание 2 (Рабочий лист)'!$E$3:$E$502) * 1000 -> 47.284215
A6: Еда | B6: =COUNTIF('Задание 2 (Рабочий лист)'!$B$3:$B$502, A6) -> 70 | C6: =AVERAGEIF('Задание 2 (Рабочий лист)'!$B$3:$B$502, A6, 'Задание 2 (Рабочий лист)'!$I$3:$I$502) -> 27329.027 | D6: =IFERROR(__xludf.DUMMYFUNCTION("MEDIAN(FILTER('Задание 2 (Рабочий лист)'!$I$3:$I$502, 'Задание 2 (Рабочий лист)'!$B$3:$B$502 = A6)) "),5262.360000000001) -> 5262.36 | E6: =SUMIF('Задание 2 (Рабочий лист)'!$B$3:$B$502, A6, 'Задание 2 (Рабочий лист)'!$I$3:$I$502) -> 1913031.9 | F6: =IFERROR(__xludf.DUMMYFUNCTION("SUM(ARRAY_CONSTRAIN(SORT(FILTER('Задание 2 (Рабочий лист)'!$I$2:$I$502, 'Задание 2 (Рабочий лист)'!$B$2:$B$502 = A6), 1, FALSE), ROUND(COUNTIF('Задание 2 (Рабочий лист)'!$B$2:$B$502, A6) * 0.1), 1)) / SUMIF('Задание 2 (Рабочий лист)'!$B$2:$B$502, A6, 'Зад"&"ание 2 (Рабочий лист)'!$I$2:$I$502) "),0.5395711600955776) -> 0.53957116 | G6: =AVERAGEIF('Задание 2 (Рабочий лист)'!$B$3:$B$502, A6, 'Задание 2 (Рабочий лист)'!$E$3:$E$502) -> 614135.06 | H6: =SUMIF('Задание 2 (Рабочий лист)'!$B$3:$B$502, A6, 'Задание 2 (Рабочий лист)'!$H$3:$H$502) / SUMIF('Задание 2 (Рабочий лист)'!$B$3:$B$502, A6, 'Задание 2 (Рабочий лист)'!$E$3:$E$502) * 1000 -> 5.4276567 | I6: =SUMIF('Задание 2 (Рабочий лист)'!$B$3:$B$502, A6, 'Задание 2 (Рабочий лист)'!$G$3:$G$502) / SUMIF('Задание 2 (Рабочий лист)'!$B$3:$B$502, A6, 'Задание 2 (Рабочий лист)'!$E$3:$E$502) * 1000 -> 88.8915 | J6: =SUMIF('Задание 2 (Рабочий лист)'!$B$3:$B$502, A6, 'Задание 2 (Рабочий лист)'!$I$3:$I$502) / SUMIF('Задание 2 (Рабочий лист)'!$B$3:$B$502, A6, 'Задание 2 (Рабочий лист)'!$E$3:$E$502) * 1000 -> 44.500027
A7: Развлечения | B7: =COUNTIF('Задание 2 (Рабочий лист)'!$B$3:$B$502, A7) -> 150 | C7: =AVERAGEIF('Задание 2 (Рабочий лист)'!$B$3:$B$502, A7, 'Задание 2 (Рабочий лист)'!$I$3:$I$502) -> 18187.248 | D7: =IFERROR(__xludf.DUMMYFUNCTION("MEDIAN(FILTER('Задание 2 (Рабочий лист)'!$I$3:$I$502, 'Задание 2 (Рабочий лист)'!$B$3:$B$502 = A7)) "),2477.755) -> 2477.755 | E7: =SUMIF('Задание 2 (Рабочий лист)'!$B$3:$B$502, A7, 'Задание 2 (Рабочий лист)'!$I$3:$I$502) -> 2728087.2 | F7: =IFERROR(__xludf.DUMMYFUNCTION("SUM(ARRAY_CONSTRAIN(SORT(FILTER('Задание 2 (Рабочий лист)'!$I$2:$I$502, 'Задание 2 (Рабочий лист)'!$B$2:$B$502 = A7), 1, FALSE), ROUND(COUNTIF('Задание 2 (Рабочий лист)'!$B$2:$B$502, A7) * 0.1), 1)) / SUMIF('Задание 2 (Рабочий лист)'!$B$2:$B$502, A7, 'Зад"&"ание 2 (Рабочий лист)'!$I$2:$I$502) "),0.8182565028777071) -> 0.8182565 | G7: =AVERAGEIF('Задание 2 (Рабочий лист)'!$B$3:$B$502, A7, 'Задание 2 (Рабочий лист)'!$E$3:$E$502) -> 362877.82 | H7: =SUMIF('Задание 2 (Рабочий лист)'!$B$3:$B$502, A7, 'Задание 2 (Рабочий лист)'!$H$3:$H$502) / SUMIF('Задание 2 (Рабочий лист)'!$B$3:$B$502, A7, 'Задание 2 (Рабочий лист)'!$E$3:$E$502) * 1000 -> 5.7075409 | I7: =SUMIF('Задание 2 (Рабочий лист)'!$B$3:$B$502, A7, 'Задание 2 (Рабочий лист)'!$G$3:$G$502) / SUMIF('Задание 2 (Рабочий лист)'!$B$3:$B$502, A7, 'Задание 2 (Рабочий лист)'!$E$3:$E$502) * 1000 -> 100.12481 | J7: =SUMIF('Задание 2 (Рабочий лист)'!$B$3:$B$502, A7, 'Задание 2 (Рабочий лист)'!$I$3:$I$502) / SUMIF('Задание 2 (Рабочий лист)'!$B$3:$B$502, A7, 'Задание 2 (Рабочий лист)'!$E$3:$E$502) * 1000 -> 50.119481
A9: Дополнительные столбцы помогают проверить гипотезу: темы с более высокой вовлечённостью и просмотрами обычно дают больший бюджет выплат.

Sheet Задание 2 (Инструкция)
B2: Дано
B3: 1. | C3: Рабочий лист
C4: – Лист на котором нужно производить все расчеты
C5: – У тебя есть ID автора и его тематика
C6: – Остальные столбики нужно заполнить самостоятельно, используя данные с листа (Известные данные) и параметры на листе (Справочник)
B8: 2. | C8: Справочник
D9: Тематики
D10: – Доля подписчиков, которые постоянно смотрят авторов в каждой тематике
D11: – Доля новых зрителей от всех просмотров автора в каждой тематике
D12: – Сегменты по подписчикам
D13: – Пороговые значения для кажого сегмента
D14: – Вовлеченность
D15: – Доля реакций от просмотров для каждого сегмента
B17: 3. | C17: Таблица с известными данными по кажому автору за месяц
D18: – Подписчики
D19: – Рекламные показы
D20: – Рекламный CPM
B22: Рассчитать
B23: 1. | C23: Просмотры
D24: Не все подписчики смотрят видео — только доля из справочника. Кроме того, часть просмотров приходит от неподписанных зрителей. Их доля от общего числа просмотров — это второй процент из того же справочника. Полученный результат нужно округлить ло целого
B26: 2. | C26: Выручка
D27: Зависит от рекламных показов и CPM (стоимость 1000 показов).
B29: 3. | C29: Вовлеченность
D30: Сначала определить сегмент автора по подписчикам. Затем взять из справочника долю реакций от просмотров для этого сегмента и рассчитать вовлечённость на основе просмотров.
B32: 4. | C32: Выплата
D33: Посчитать выплату по каждому автору, используя метод, который ты выбрал в Задании 1

Sheet Задание 2 (Рабочий лист)
A2: ID | B2: Тематика | C2: Сегмент по подписчикам | D2: Подписчики | E2: Просмотры | F2: Рекламные показы | G2: Выручка | H2: Вовлеченность | I2: Выплата
A3: Автор 1 | B3: Детский контент | C3: =IF(D3>=500000,"Большой",IF(D3>=100000,"Средний","Маленький")) -> Большой | D3: =VLOOKUP(A3,'Задание 2 (Известные данные)'!$A$2:$D$501,2,FALSE) -> 3456789 | E3: =ROUND(D3*VLOOKUP(B3,'Задание 2 (Справочник)'!$B$8:$D$12,2,FALSE)/(1-VLOOKUP(B3,'Задание 2 (Справочник)'!$B$8:$D$12,3,FALSE)),0) -> 3950616 | F3: =VLOOKUP(A3,'Задание 2 (Известные данные)'!$A$2:$D$501,3,FALSE) -> 2281481 | G3: =F3*VLOOKUP(A3,'Задание 2 (Известные данные)'!$A$2:$D$501,4,FALSE)/1000 -> 355911.04 | H3: =ROUND(E3*VLOOKUP(C3,'Задание 2 (Справочник)'!$B$16:$C$18,2,FALSE),0) -> 19753 | I3: =ROUND(G3*0.5+H3*0.01,2) -> 178153.05
A4: Автор 2 | B4: Детский контент | C4: =IF(D4>=500000,"Большой",IF(D4>=100000,"Средний","Маленький")) -> Большой | D4: =VLOOKUP(A4,'Задание 2 (Известные данные)'!$A$2:$D$501,2,FALSE) -> 2876543 | E4: =ROUND(D4*VLOOKUP(B4,'Задание 2 (Справочник)'!$B$8:$D$12,2,FALSE)/(1-VLOOKUP(B4,'Задание 2 (Справочник)'!$B$8:$D$12,3,FALSE)),0) -> 3287478 | F4: =VLOOKUP(A4,'Задание 2 (Известные данные)'!$A$2:$D$501,3,FALSE) -> 1898518 | G4: =F4*VLOOKUP(A4,'Задание 2 (Известные данные)'!$A$2:$D$501,4,FALSE)/1000 -> 254401.41 | H4: =ROUND(E4*VLOOKUP(C4,'Задание 2 (Справочник)'!$B$16:$C$18,2,FALSE),0) -> 16437 | I4: =ROUND(G4*0.5+H4*0.01,2) -> 127365.08
A5: Автор 3 | B5: Детский контент | C5: =IF(D5>=500000,"Большой",IF(D5>=100000,"Средний","Маленький")) -> Большой | D5: =VLOOKUP(A5,'Задание 2 (Известные данные)'!$A$2:$D$501,2,FALSE) -> 4123987 | E5: =ROUND(D5*VLOOKUP(B5,'Задание 2 (Справочник)'!$B$8:$D$12,2,FALSE)/(1-VLOOKUP(B5,'Задание 2 (Справочник)'!$B$8:$D$12,3,FALSE)),0) -> 4713128 | F5: =VLOOKUP(A5,'Задание 2 (Известные данные)'!$A$2:$D$501,3,FALSE) -> 2721832 | G5: =F5*VLOOKUP(A5,'Задание 2 (Известные данные)'!$A$2:$D$501,4,FALSE)/1000 -> 484486.1 | H5: =ROUND(E5*VLOOKUP(C5,'Задание 2 (Справочник)'!$B$16:$C$18,2,FALSE),0) -> 23566 | I5: =ROUND(G5*0.5+H5*0.01,2) -> 242478.71
A6: Автор 4 | B6: Детский контент | C6: =IF(D6>=500000,"Большой",IF(D6>=100000,"Средний","Маленький")) -> Большой | D6: =VLOOKUP(A6,'Задание 2 (Известные данные)'!$A$2:$D$501,2,FALSE) -> 1987654 | E6: =ROUND(D6*VLOOKUP(B6,'Задание 2 (Справочник)'!$B$8:$D$12,2,FALSE)/(1-VLOOKUP(B6,'Задание 2 (Справочник)'!$B$8:$D$12,3,FALSE)),0) -> 2271605 | F6: =VLOOKUP(A6,'Задание 2 (Известные данные)'!$A$2:$D$501,3,FALSE) -> 1311851 | G6: =F6*VLOOKUP(A6,'Задание 2 (Известные данные)'!$A$2:$D$501,4,FALSE)/1000 -> 146927.31 | H6: =ROUND(E6*VLOOKUP(C6,'Задание 2 (Справочник)'!$B$16:$C$18,2,FALSE),0) -> 11358 | I6: =ROUND(G6*0.5+H6*0.01,2) -> 73577.24
A7: Автор 5 | B7: Детский контент | C7: =IF(D7>=500000,"Большой",IF(D7>=100000,"Средний","Маленький")) -> Большой | D7: =VLOOKUP(A7,'Задание 2 (Известные данные)'!$A$2:$D$501,2,FALSE) -> 5234012 | E7: =ROUND(D7*VLOOKUP(B7,'Задание 2 (Справочник)'!$B$8:$D$12,2,FALSE)/(1-VLOOKUP(B7,'Задание 2 (Справочник)'!$B$8:$D$12,3,FALSE)),0) -> 5981728 | F7: =VLOOKUP(A7,'Задание 2 (Известные данные)'!$A$2:$D$501,3,FALSE) -> 3454448 | G7: =F7*VLOOKUP(A7,'Задание 2 (Известные данные)'!$A$2:$D$501,4,FALSE)/1000 -> 652890.67 | H7: =ROUND(E7*VLOOKUP(C7,'Задание 2 (Справочник)'!$B$16:$C$18,2,FALSE),0) -> 29909 | I7: =ROUND(G7*0.5+H7*0.01,2) -> 326744.43
A8: Автор 6 | B8: Детский контент | C8: =IF(D8>=500000,"Большой",IF(D8>=100000,"Средний","Маленький")) -> Большой | D8: =VLOOKUP(A8,'Задание 2 (Известные данные)'!$A$2:$D$501,2,FALSE) -> 2765432 | E8: =ROUND(D8*VLOOKUP(B8,'Задание 2 (Справочник)'!$B$8:$D$12,2,FALSE)/(1-VLOOKUP(B8,'Задание 2 (Справочник)'!$B$8:$D$12,3,FALSE)),0) -> 3160494 | F8: =VLOOKUP(A8,'Задание 2 (Известные данные)'!$A$2:$D$501,3,FALSE) -> 1825185 | G8: =F8*VLOOKUP(A8,'Задание 2 (Известные данные)'!$A$2:$D$501,4,FALSE)/1000 -> 264651.83 | H8: =ROUND(E8*VLOOKUP(C8,'Задание 2 (Справочник)'!$B$16:$C$18,2,FALSE),0) -> 15802 | I8: =ROUND(G8*0.5+H8*0.01,2) -> 132483.93
A9: Автор 7 | B9: Детский контент | C9: =IF(D9>=500000,"Большой",IF(D9>=100000,"Средний","Маленький")) -> Большой | D9: =VLOOKUP(A9,'Задание 2 (Известные данные)'!$A$2:$D$501,2,FALSE) -> 3987612 | E9: =ROUND(D9*VLOOKUP(B9,'Задание 2 (Справочник)'!$B$8:$D$12,2,FALSE)/(1-VLOOKUP(B9,'Задание 2 (Справочник)'!$B$8:$D$12,3,FALSE)),0) -> 4557271 | F9: =VLOOKUP(A9,'Задание 2 (Известные данные)'!$A$2:$D$501,3,FALSE) -> 2631824 | G9: =F9*VLOOKUP(A9,'Задание 2 (Известные данные)'!$A$2:$D$501,4,FALSE)/1000 -> 439514.61 | H9: =ROUND(E9*VLOOKUP(C9,'Задание 2 (Справочник)'!$B$16:$C$18,2,FALSE),0) -> 22786 | I9: =ROUND(G9*0.5+H9*0.01,2) -> 219985.16
A10: Автор 8 | B10: Детский контент | C10: =IF(D10>=500000,"Большой",IF(D10>=100000,"Средний","Маленький")) -> Большой | D10: =VLOOKUP(A10,'Задание 2 (Известные данные)'!$A$2:$D$501,2,FALSE) -> 1876543 | E10: =ROUND(D10*VLOOKUP(B10,'Задание 2 (Справочник)'!$B$8:$D$12,2,FALSE)/(1-VLOOKUP(B10,'Задание 2 (Справочник)'!$B$8:$D$12,3,FALSE)),0) -> 2144621 | F10: =VLOOKUP(A10,'Задание 2 (Известные данные)'!$A$2:$D$501,3,FALSE) -> 1238518 | G10: =F10*VLOOKUP(A10,'Задание 2 (Известные данные)'!$A$2:$D$501,4,FALSE)/1000 -> 152337.71 | H10: =ROUND(E10*VLOOKUP(C10,'Задание 2 (Справочник)'!$B$16:$C$18,2,FALSE),0) -> 10723 | I10: =ROUND(G10*0.5+H10*0.01,2) -> 76276.09
A11: Автор 9 | B11: Детский контент | C11: =IF(D11>=500000,"Большой",IF(D11>=100000,"Средний","Маленький")) -> Большой | D11: =VLOOKUP(A11,'Задание 2 (Известные данные)'!$A$2:$D$501,2,FALSE) -> 4509876 | E11: =ROUND(D11*VLOOKUP(B11,'Задание 2 (Справочник)'!$B$8:$D$12,2,FALSE)/(1-VLOOKUP(B11,'Задание 2 (Справочник)'!$B$8:$D$12,3,FALSE)),0) -> 5154144 | F11: =VLOOKUP(A11,'Задание 2 (Известные данные)'!$A$2:$D$501,3,FALSE) -> 2976518 | G11: =F11*VLOOKUP(A11,'Задание 2 (Известные данные)'!$A$2:$D$501,4,FALSE)/1000 -> 571491.46 | H11: =ROUND(E11*VLOOKUP(C11,'Задание 2 (Справочник)'!$B$16:$C$18,2,FALSE),0) -> 25771 | I11: =ROUND(G11*0.5+H11*0.01,2) -> 286003.44
A12: Автор 10 | B12: Детский контент | C12: =IF(D12>=500000,"Большой",IF(D12>=100000,"Средний","Маленький")) -> Большой | D12: =VLOOKUP(A12,'Задание 2 (Известные данные)'!$A$2:$D$501,2,FALSE) -> 2345678 | E12: =ROUND(D12*VLOOKUP(B12,'Задание 2 (Справочник)'!$B$8:$D$12,2,FALSE)/(1-VLOOKUP(B12,'Задание 2 (Справочник)'!$B$8:$D$12,3,FALSE)),0) -> 2680775 | F12: =VLOOKUP(A12,'Задание 2 (Известные данные)'!$A$2:$D$501,3,FALSE) -> 1548148 | G12: =F12*VLOOKUP(A12,'Задание 2 (Известные данные)'!$A$2:$D$501,4,FALSE)/1000 -> 167199.98 | H12: =ROUND(E12*VLOOKUP(C12,'Задание 2 (Справочник)'!$B$16:$C$18,2,FALSE),0) -> 13404 | I12: =ROUND(G12*0.5+H12*0.01,2) -> 83734.03
A13: Автор 11 | B13: Детский контент | C13: =IF(D13>=500000,"Большой",IF(D13>=100000,"Средний","Маленький")) -> Большой | D13: =VLOOKUP(A13,'Задание 2 (Известные данные)'!$A$2:$D$501,2,FALSE) -> 3678901 | E13: =ROUND(D13*VLOOKUP(B13,'Задание 2 (Справочник)'!$B$8:$D$12,2,FALSE)/(1-VLOOKUP(B13,'Задание 2 (Справочник)'!$B$8:$D$12,3,FALSE)),0) -> 4204458 | F13: =VLOOKUP(A13,'Задание 2 (Известные данные)'!$A$2:$D$501,3,FALSE) -> 2428075 | G13: =F13*VLOOKUP(A13,'Задание 2 (Известные данные)'!$A$2:$D$501,4,FALSE)/1000 -> 422485.05 | H13: =ROUND(E13*VLOOKUP(C13,'Задание 2 (Справочник)'!$B$16:$C$18,2,FALSE),0) -> 21022 | I13: =ROUND(G13*0.5+H13*0.01,2) -> 211452.75
A14: Автор 12 | B14: Детский контент | C14: =IF(D14>=500000,"Большой",IF(D14>=100000,"Средний","Маленький")) -> Большой | D14: =VLOOKUP(A14,'Задание 2 (Известные данные)'!$A$2:$D$501,2,FALSE) -> 2987654 | E14: =ROUND(D14*VLOOKUP(B14,'Задание 2 (Справочник)'!$B$8:$D$12,2,FALSE)/(1-VLOOKUP(B14,'Задание 2 (Справочник)'!$B$8:$D$12,3,FALSE)),0) -> 3414462 | F14: =VLOOKUP(A14,'Задание 2 (Известные данные)'!$A$2:$D$501,3,FALSE) -> 1971851 | G14: =F14*VLOOKUP(A14,'Задание 2 (Известные данные)'!$A$2:$D$501,4,FALSE)/1000 -> 274087.29 | H14: =ROUND(E14*VLOOKUP(C14,'Задание 2 (Справочник)'!$B$16:$C$18,2,FALSE),0) -> 17072 | I14: =ROUND(G14*0.5+H14*0.01,2) -> 137214.36
... A502: Автор 500 | B502: Развлечения | C502: =IF(D502>=500000,"Большой",IF(D502>=100000,"Средний","Маленький")) -> Маленький | D502: =VLOOKUP(A502,'Задание 2 (Известные данные)'!$A$2:$D$501,2,FALSE) -> 43210 | E502: =ROUND(D502*VLOOKUP(B502,'Задание 2 (Справочник)'!$B$8:$D$12,2,FALSE)/(1-VLOOKUP(B502,'Задание 2 (Справочник)'!$B$8:$D$12,3,FALSE)),0) -> 36008 | F502: =VLOOKUP(A502,'Задание 2 (Известные данные)'!$A$2:$D$501,3,FALSE) -> 27222 | G502: =F502*VLOOKUP(A502,'Задание 2 (Известные данные)'!$A$2:$D$501,4,FALSE)/1000 -> 2504.424 | H502: =ROUND(E502*VLOOKUP(C502,'Задание 2 (Справочник)'!$B$16:$C$18,2,FALSE),0) -> 360 | I502: =ROUND(G502*0.5+H502*0.01,2) -> 1255.81

Sheet Задание 2 (Справочник)
B1: Сегмент по подписчикам | C1: Кол-во подписчиков
B2: Большой | C2: от 500 тыс
B3: Средний | C3: 100 – 500 тыс
B4: Маленький | C4: до 100 тыс
B7: Тематика | C7: Какой % подписчиков смотрит авторов | D7: Доля новых зрителей от общего числа просмотров
B8: Детский контент | C8: 0.8 | D8: 0.3
B9: Спорт | C9: 0.75 | D9: 0.3
B10: Игры | C10: 0.9 | D10: 0.1
B11: Еда | C11: 0.6 | D11: 0.2
B12: Развлечения | C12: 0.5 | D12: 0.4
B15: Сегмент по подписчикам | C15: Вовлеченность
B16: Большой | C16: 0.005
B17: Средний | C17: 0.0075
B18: Маленький | C18: 0.01

Sheet Задание 2 (Известные данные)
A1: ID | B1: Подписчики | C1: Рекламные показы | D1: Рекламный CPM
A2: Автор 91 | B2: 4509876 | C2: 3314759 | D2: 199
A3: Автор 87 | B3: 4234567 | C3: 3112407 | D3: 196
A4: Автор 15 | B4: 5123987 | C4: 3381832 | D4: 195
A5: Автор 103 | B5: 4234567 | C5: 3112407 | D5: 195
A6: Автор 9 | B6: 4509876 | C6: 2976518 | D6: 192
A7: Автор 82 | B7: 3987612 | C7: 2930895 | D7: 192
A8: Автор 98 | B8: 3987612 | C8: 2930895 | D8: 191
A9: Автор 5 | B9: 5234012 | C9: 3454448 | D9: 189
A10: Автор 86 | B10: 3456789 | C10: 2540740 | D10: 189
A11: Автор 102 | B11: 3456789 | C11: 2540740 | D11: 188
A12: Автор 100 | B12: 5123987 | C12: 3766130 | D12: 186
A13: Автор 84 | B13: 5123987 | C13: 3766130 | D13: 185
... A501: Автор 76 | B501: 12345 | C501: 8148 | D501: 46
